{"playlist":{"subscribers":[],"subscribed":false,"creator":{"defaultAvatar":false,"province":110000,"authStatus":0,"followed":false,"avatarUrl":"http://p1.music.126.net/d8faOLHxwWPta02fskrdDQ==/2057186255569164.jpg","accountStatus":0,"gender":2,"city":110101,"birthday":-2209017600000,"userId":48188,"userType":0,"nickname":"中国TOP排行榜","signature":"中国TOP排行榜是由MusicRadio音乐之声依据时下最热门的流行单曲形成的权威音乐榜单。","description":"","detailDescription":"","avatarImgId":2057186255569164,"backgroundImgId":2002210674180201,"backgroundUrl":"http://p1.music.126.net/o3G7lWrGBQAvSRt3UuApTw==/2002210674180201.jpg","authority":0,"mutual":false,"expertTags":null,"experts":null,"djStatus":0,"vipType":0,"remarkName":null,"avatarImgIdStr":"2057186255569164","backgroundImgIdStr":"2002210674180201"},"tracks":[{"name":"慢慢喜欢你","id":541687281,"pst":0,"t":0,"ar":[{"id":8926,"name":"莫文蔚","tns":[],"alias":[]}],"alia":[],"pop":100.0,"st":0,"rt":null,"fee":8,"v":5,"crbt":null,"cf":"","al":{"id":37561940,"name":"慢慢喜欢你","picUrl":"http://p1.music.126.net/XqNiBR_6gPXXq58vW2dD8g==/109951163169448520.jpg","tns":[],"pic_str":"109951163169448520","pic":109951163169448520},"dt":221022,"h":{"br":320000,"fid":0,"size":8841970,"vd":0.0},"m":{"br":192000,"fid":0,"size":5305200,"vd":0.0},"l":{"br":128000,"fid":0,"size":3536814,"vd":0.0},"a":null,"cd":"1","no":1,"rtUrl":null,"ftype":0,"rtUrls":[],"djId":0,"copyright":2,"s_id":0,"mst":9,"cp":7001,"mv":0,"rurl":null,"rtype":0,"publishTime":1519920000007},{"name":"重来","id":529747142,"pst":0,"t":0,"ar":[{"id":7214,"name":"蔡健雅","tns":[],"alias":[]}],"alia":[],"pop":100.0,"st":0,"rt":null,"fee":8,"v":6,"crbt":null,"cf":"","al":{"id":37121577,"name":"割爱","picUrl":"http://p1.music.126.net/FWECW2UFsWN4hv1_UD57Bg==/109951163105324107.jpg","tns":[],"pic_str":"109951163105324107","pic":109951163105324107},"dt":282749,"h":{"br":320000,"fid":0,"size":11311064,"vd":0.0},"m":{"br":192000,"fid":0,"size":6786656,"vd":0.0},"l":{"br":128000,"fid":0,"size":4524452,"vd":0.0},"a":null,"cd":"1","no":1,"rtUrl":null,"ftype":0,"rtUrls":[],"djId":0,"copyright":1,"s_id":0,"mst":9,"cp":7003,"mv":0,"rurl":null,"rtype":0,"publishTime":1515686400007},{"name":"Ten Reasons","id":543987746,"pst":0,"t":0,"ar":[{"id":2738,"name":"方大同","tns":[],"alias":[]}],"alia":[],"pop":100.0,"st":0,"rt":null,"fee":4,"v":5,"crbt":null,"cf":"","al":{"id":37886134,"name":"Ten Reasons","picUrl":"http://p1.music.126.net/5K36tL_ijyoBcwp_zrD4ng==/109951163185995760.jpg","tns":[],"pic_str":"109951163185995760","pic":109951163185995760},"dt":224500,"h":{"br":320000,"fid":0,"size":8983031,"vd":0.0},"m":{"br":192000,"fid":0,"size":5389836,"vd":0.0},"l":{"br":128000,"fid":0,"size":3593239,"vd":0.0},"a":null,"cd":"","no":0,"rtUrl":null,"ftype":0,"rtUrls":[],"djId":0,"copyright":0,"s_id":0,"mst":9,"cp":578013,"mv":5843291,"rurl":null,"rtype":0,"publishTime":1520870400007},{"name":"流浪的终点","id":545350071,"pst":0,"t":0,"ar":[{"id":6456,"name":"周华健","tns":[],"alias":[]}],"alia":["电影《猫与桃花源》主题曲"],"pop":100.0,"st":0,"rt":null,"fee":0,"v":13,"crbt":null,"cf":"","al":{"id":37873572,"name":"流浪的终点","picUrl":"http://p1.music.126.net/z9sJHxQVtWlfr9KCXTU_ag==/109951163188459391.jpg","tns":[],"pic_str":"109951163188459391","pic":109951163188459391},"dt":221797,"h":{"br":320000,"fid":0,"size":8874362,"vd":0.0},"m":{"br":192000,"fid":0,"size":5324635,"vd":0.0},"l":{"br":128000,"fid":0,"size":3549771,"vd":0.0},"a":null,"cd":"1","no":1,"rtUrl":null,"ftype":0,"rtUrls":[],"djId":0,"copyright":0,"s_id":0,"mst":9,"cp":641010,"mv":5853070,"rurl":null,"rtype":0,"publishTime":1520956800000},{"name":"爱是光","id":542871253,"pst":0,"t":0,"ar":[{"id":9102,"name":"彭佳慧","tns":[],"alias":[]}],"alia":["电影《花滑女王》中文主题曲"],"pop":100.0,"st":0,"rt":null,"fee":8,"v":2,"crbt":null,"cf":"","al":{"id":37767093,"name":"爱是光","picUrl":"http://p1.music.126.net/rpo12KmrBDZZ-YiAoaWYtg==/109951163171298708.jpg","tns":[],"pic_str":"109951163171298708","pic":109951163171298708},"dt":268382,"h":{"br":320000,"fid":0,"size":10735325,"vd":-1.0},"m":{"br":192000,"fid":0,"size":6441213,"vd":-1.0},"l":{"br":128000,"fid":0,"size":4294156,"vd":-1.0},"a":null,"cd":"1","no":1,"rtUrl":null,"ftype":0,"rtUrls":[],"djId":0,"copyright":1,"s_id":0,"mst":9,"cp":7001,"mv":0,"rurl":null,"rtype":0,"publishTime":1520524800007},{"name":"名不虚传","id":528270294,"pst":0,"t":0,"ar":[{"id":6463,"name":"赵传","tns":[],"alias":[]}],"alia":[],"pop":85.0,"st":0,"rt":null,"fee":0,"v":8,"crbt":null,"cf":"","al":{"id":37179103,"name":"你过得还好吗","picUrl":"http://p1.music.126.net/k9qNy1N4JT6u0ATjxNNWmA==/109951163102803204.jpg","tns":[],"pic_str":"109951163102803204","pic":109951163102803204},"dt":304800,"h":{"br":320000,"fid":0,"size":12195048,"vd":-2.0},"m":{"br":192000,"fid":0,"size":7317046,"vd":-2.0},"l":{"br":128000,"fid":0,"size":4878045,"vd":-2.0},"a":null,"cd":"1","no":2,"rtUrl":null,"ftype":0,"rtUrls":[],"djId":0,"copyright":2,"s_id":0,"mst":9,"cp":22036,"mv":0,"rurl":null,"rtype":0,"publishTime":1515340800007},{"name":"爱不得","id":534541484,"pst":0,"t":0,"ar":[{"id":6066,"name":"杨宗纬","tns":[],"alias":[]}],"alia":["电视剧《谈判官》主题曲"],"pop":100.0,"st":0,"rt":null,"fee":8,"v":91,"crbt":null,"cf":"","al":{"id":37464083,"name":"谈判官 电视原声带","picUrl":"http://p1.music.126.net/eIwn9dPflwdAwhVz0vJsng==/109951163133237974.jpg","tns":[],"pic_str":"109951163133237974","pic":109951163133237974},"dt":237618,"h":{"br":320000,"fid":0,"size":9507570,"vd":0.0},"m":{"br":192000,"fid":0,"size":5704560,"vd":0.0},"l":{"br":128000,"fid":0,"size":3803054,"vd":0.0},"a":null,"cd":"1","no":2,"rtUrl":null,"ftype":0,"rtUrls":[],"djId":0,"copyright":2,"s_id":0,"mst":9,"cp":514011,"mv":0,"rurl":null,"rtype":0,"publishTime":1519401600007},{"name":"不再","id":543986699,"pst":0,"t":0,"ar":[{"id":6454,"name":"张信哲","tns":[],"alias":[]}],"alia":[],"pop":100.0,"st":0,"rt":null,"fee":0,"v":4,"crbt":null,"cf":"","al":{"id":37887107,"name":"不再","picUrl":"http://p1.music.126.net/InKbma7iSTnfgI5sKGeEcw==/109951163185822094.jpg","tns":[],"pic_str":"109951163185822094","pic":109951163185822094},"dt":230040,"h":{"br":320000,"fid":0,"size":9204550,"vd":0.0},"m":{"br":192000,"fid":0,"size":5522747,"vd":0.0},"l":{"br":128000,"fid":0,"size":3681846,"vd":0.0},"a":null,"cd":"","no":0,"rtUrl":null,"ftype":0,"rtUrls":[],"djId":0,"copyright":0,"s_id":0,"mst":9,"cp":35015,"mv":5843529,"rurl":null,"rtype":0,"publishTime":1520870400007},{"name":"戒心伤","id":526470091,"pst":0,"t":0,"ar":[{"id":4755,"name":"品冠","tns":[],"alias":[]}],"alia":[],"pop":95.0,"st":0,"rt":null,"fee":0,"v":18,"crbt":null,"cf":"","al":{"id":37085037,"name":"言外之意","picUrl":"http://p1.music.126.net/uz82zZYMKFTrsZArRCuCvg==/109951163094309961.jpg","tns":[],"pic_str":"109951163094309961","pic":109951163094309961},"dt":210216,"h":{"br":320000,"fid":0,"size":8411472,"vd":0.0},"m":{"br":192000,"fid":0,"size":5046901,"vd":0.0},"l":{"br":128000,"fid":0,"size":3364615,"vd":0.0},"a":null,"cd":"","no":2,"rtUrl":null,"ftype":0,"rtUrls":[],"djId":0,"copyright":0,"s_id":0,"mst":9,"cp":14026,"mv":5842059,"rurl":null,"rtype":0,"publishTime":1514390400007},{"name":"最久的瞬间","id":534064533,"pst":0,"t":0,"ar":[{"id":6208,"name":"炎亚纶","tns":[],"alias":[]}],"alia":["电视剧《一路繁花相送》主题曲"],"pop":100.0,"st":0,"rt":null,"fee":8,"v":15,"crbt":null,"cf":"","al":{"id":37444172,"name":"最久的瞬间","picUrl":"http://p1.music.126.net/_FgXYZSvdVwwCbHuQ6bXUQ==/109951163167881755.jpg","tns":[],"pic_str":"109951163167881755","pic":109951163167881755},"dt":230704,"h":{"br":320000,"fid":0,"size":9230672,"vd":-2.0},"m":{"br":192000,"fid":0,"size":5538421,"vd":-1.0},"l":{"br":128000,"fid":0,"size":3692295,"vd":-1.0},"a":null,"cd":"","no":0,"rtUrl":null,"ftype":0,"rtUrls":[],"djId":0,"copyright":0,"s_id":0,"mst":9,"cp":677020,"mv":5842137,"rurl":null,"rtype":0,"publishTime":1517414400007},{"name":"新宠","id":541422032,"pst":0,"t":0,"ar":[{"id":10387,"name":"阎奕格","tns":[],"alias":[]}],"alia":["偶像剧《逃婚一百次》片尾曲 / bano传奇水广告歌曲 / New Love"],"pop":90.0,"st":0,"rt":null,"fee":8,"v":72,"crbt":null,"cf":"","al":{"id":37542537,"name":"我有我自己","picUrl":"http://p1.music.126.net/OTC4LWppgU-6d2U81QE8oA==/109951163167868077.jpg","tns":[],"pic_str":"109951163167868077","pic":109951163167868077},"dt":291574,"h":{"br":320000,"fid":0,"size":11665285,"vd":0.0},"m":{"br":192000,"fid":0,"size":6999188,"vd":0.0},"l":{"br":128000,"fid":0,"size":4666140,"vd":0.0},"a":null,"cd":"1","no":4,"rtUrl":null,"ftype":0,"rtUrls":[],"djId":0,"copyright":2,"s_id":0,"mst":9,"cp":677020,"mv":5842150,"rurl":null,"rtype":0,"publishTime":1508428800000},{"name":"Despacito 缓缓","id":532777048,"pst":0,"t":0,"ar":[{"id":38154,"name":"Luis Fonsi","tns":[],"alias":[]},{"id":3684,"name":"林俊杰","tns":[],"alias":[]}],"alia":[],"pop":100.0,"st":0,"rt":null,"fee":4,"v":7,"crbt":null,"cf":"","al":{"id":37251646,"name":"Despacito 缓缓","picUrl":"http://p1.music.126.net/kTf5saXL2fCvTAzCZemTvg==/109951163118071937.jpg","tns":[],"pic_str":"109951163118071937","pic":109951163118071937},"dt":229381,"h":{"br":320000,"fid":0,"size":9176338,"vd":-3.0},"m":{"br":192000,"fid":0,"size":5505820,"vd":-2.0},"l":{"br":128000,"fid":0,"size":3670561,"vd":-2.0},"a":null,"cd":"1","no":1,"rtUrl":null,"ftype":0,"rtUrls":[],"djId":0,"copyright":0,"s_id":0,"mst":9,"cp":7003,"mv":0,"rurl":null,"rtype":0,"publishTime":1516924800000}],"trackIds":[{"id":541687281,"v":5,"lr":0},{"id":529747142,"v":6,"lr":2},{"id":543987746,"v":5},{"id":545350071,"v":13},{"id":542871253,"v":2},{"id":528270294,"v":8},{"id":534541484,"v":91,"lr":3},{"id":543986699,"v":4,"lr":1},{"id":526470091,"v":18,"lr":5},{"id":534064533,"v":15,"lr":4},{"id":541422032,"v":72,"lr":10},{"id":532777048,"v":7,"lr":6}],"status":0,"trackNumberUpdateTime":1522671416760,"adType":0,"cloudTrackCount":0,"subscribedCount":70392,"userId":48188,"ordered":true,"tags":["流行"],"newImported":false,"privacy":0,"coverImgId":18967675090783713,"createTime":1359697325722,"updateTime":1522671416817,"specialType":10,"highQuality":false,"commentThreadId":"A_PL_0_112504","trackUpdateTime":1522671416827,"trackCount":12,"coverImgUrl":"http://p1.music.126.net/JPh-zekmt0sW2Z3TZMsGzA==/18967675090783713.jpg","playCount":21680640,"description":"中国TOP排行榜分成内地榜及港台榜，每周一更新。","name":"中国TOP排行榜（港台榜）","id":112504,"shareCount":176,"coverImgId_str":"18967675090783713","commentCount":950},"code":200,"privileges":[{"id":541687281,"fee":0,"payed":0,"st":0,"pl":320000,"dl":0,"sp":7,"cp":1,"subp":1,"cs":false,"maxbr":320000,"fl":128000,"toast":false,"flag":0,"preSell":false},{"id":529747142,"fee":8,"payed":0,"st":0,"pl":128000,"dl":128000,"sp":7,"cp":1,"subp":1,"cs":false,"maxbr":320000,"fl":128000,"toast":false,"flag":4,"preSell":false},{"id":543987746,"fee":4,"payed":0,"st":0,"pl":0,"dl":0,"sp":0,"cp":0,"subp":0,"cs":false,"maxbr":999000,"fl":0,"toast":false,"flag":0,"preSell":false},{"id":545350071,"fee":0,"payed":0,"st":0,"pl":320000,"dl":320000,"sp":7,"cp":1,"subp":1,"cs":false,"maxbr":999000,"fl":320000,"toast":false,"flag":0,"preSell":false},{"id":542871253,"fee":8,"payed":0,"st":0,"pl":128000,"dl":0,"sp":7,"cp":1,"subp":1,"cs":false,"maxbr":320000,"fl":128000,"toast":false,"flag":0,"preSell":false},{"id":528270294,"fee":0,"payed":0,"st":0,"pl":320000,"dl":320000,"sp":7,"cp":1,"subp":1,"cs":false,"maxbr":999000,"fl":320000,"toast":false,"flag":0,"preSell":false},{"id":534541484,"fee":8,"payed":0,"st":0,"pl":128000,"dl":0,"sp":7,"cp":1,"subp":1,"cs":false,"maxbr":999000,"fl":128000,"toast":false,"flag":0,"preSell":false},{"id":543986699,"fee":0,"payed":0,"st":0,"pl":999000,"dl":0,"sp":7,"cp":1,"subp":1,"cs":false,"maxbr":999000,"fl":320000,"toast":false,"flag":0,"preSell":false},{"id":526470091,"fee":0,"payed":0,"st":0,"pl":320000,"dl":320000,"sp":7,"cp":1,"subp":1,"cs":false,"maxbr":999000,"fl":320000,"toast":false,"flag":0,"preSell":false},{"id":534064533,"fee":8,"payed":0,"st":0,"pl":128000,"dl":0,"sp":7,"cp":1,"subp":1,"cs":false,"maxbr":999000,"fl":128000,"toast":false,"flag":0,"preSell":false},{"id":541422032,"fee":8,"payed":0,"st":0,"pl":128000,"dl":0,"sp":7,"cp":1,"subp":1,"cs":false,"maxbr":999000,"fl":128000,"toast":false,"flag":0,"preSell":false},{"id":532777048,"fee":4,"payed":0,"st":0,"pl":0,"dl":0,"sp":0,"cp":0,"subp":0,"cs":false,"maxbr":320000,"fl":0,"toast":false,"flag":0,"preSell":false}]}